finite_difference/FD.py
finite_difference/__init__.py
finite_difference/progress.txt
finite_difference/test.py
finite_difference-0.0.3.dist-info/METADATA
finite_difference-0.0.3.dist-info/WHEEL
finite_difference-0.0.3.dist-info/licenses/LICENSE
finite_difference-0.0.3.dist-info/RECORD
