Metadata-Version: 2.1
Name: finite_difference
Version: 0.0.3
Summary: Library for setting up finite difference problems
Project-URL: Homepage, https://github.com/Ephraim-Bryski/Finite-Difference
Project-URL: Bug Tracker, https://github.com/Ephraim-Bryski/Finite-Difference/issues
Author-email: Ephraim Bryski <ebryski1@gmail.com>
License-File: LICENSE
Classifier: License :: OSI Approved :: MIT License
Classifier: Operating System :: OS Independent
Classifier: Programming Language :: Python :: 3
Requires-Python: >=3
